{
	"BublApp":
	{
		"type": "View",
		"id": "properties",
		"title": "'Properties",
		"show": true,
		"size": { "width": "max", "height": "max" },
		"layout": { "style": "vertical" },
		"defaults": { 
			"type": "View",
			"show": true,
			"size": { "width": "max", "height": "max" },
			"layout": { "style": "vertical", "align": "left" } 
		},
		"children": [
			{
				"id": "mainRow",
				"layout": { "style": "horizontal" },
				"children":[
					{
						"id": "leftPadding"
					},
					{
						"type": "View",
						"id": "mainContentArea",
						"size": { "width" : 800, "height": 600 },
						"children":[
							{
								"children": [
									{
										"type": "Control",
										"id": "header",
										"size": { "height": 40 },
										"label": "<h2>Properties</h2>"
									},
									{
										"type": "Contol",
										"label": "<p>properties of an object.</p>",
										"size": { "height": 30 }	
									},
									{
										"type": "View",
										"id": "propertiesForm",
										"children": []
									},
									{
										"type": "View",
										"layout": { "style": "horizontal" },
										"children": [
											{
												"type": "IconLabel",
												"tag": "save",
												"content": {
													"label": "Save",
													"icon": "fa-floppy-o"
												},
												"size": { "width" : 60 }
											},
											{
												"type": "IconLabel",
												"tag": "cancel",
												"content": {
													"label": "Cancel",
													"icon": "fa-thumbs-o-down"
												},
												"size": { "width" : 80 }
											}
										]
									}
								]
							}
						]
					},
					{
						"id": "rightPadding"					
					}
				]
			},
			{
				"id": "bottomPadding",
				"size": { "height" : 40 }
			}
		]
	}
}